[
 {
  "directory": "d:\\workspace\\ArduinoProjects\\weather station\\summer_17_12_21\\weather_Station_without_rf",
  "arguments": [
   "C:\\Users\\5491\\AppData\\Local\\arduino15\\packages\\arduino\\tools\\avr-gcc\\7.3.0-atmel3.6.1-arduino7/bin/avr-g++",
   "-c",
   "-g",
   "-Os",
   "-w",
   "-std=gnu++11",
   "-fpermissive",
   "-fno-exceptions",
   "-ffunction-sections",
   "-fdata-sections",
   "-fno-threadsafe-statics",
   "-Wno-error=narrowing",
   "-MMD",
   "-flto",
   "-mmcu=atmega328p",
   "-DF_CPU=16000000L",
   "-DARDUINO=10607",
   "-DARDUINO_AVR_NANO",
   "-DARDUINO_ARCH_AVR",
   "-IC:\\Users\\5491\\AppData\\Local\\arduino15\\packages\\arduino\\hardware\\avr\\1.8.6\\cores\\arduino",
   "-IC:\\Users\\5491\\AppData\\Local\\arduino15\\packages\\arduino\\hardware\\avr\\1.8.6\\variants\\eightanaloginputs",
   "-IC:\\Users\\5491\\Documents\\Arduino\\libraries\\ClosedCube_HDC1080\\src",
   "-IC:\\Users\\5491\\Documents\\Arduino\\libraries\\DHT_sensor_library_for_ESPx",
   "-IC:\\Users\\5491\\AppData\\Local\\arduino15\\packages\\arduino\\hardware\\avr\\1.8.6\\libraries\\Wire\\src",
   "-IC:\\Users\\5491\\Documents\\Arduino\\libraries\\DFRobot_SHT20",
   "-IC:\\Users\\5491\\Documents\\Arduino\\libraries\\LiquidCrystal_I2C",
   "-IC:\\Users\\5491\\Documents\\Arduino\\libraries\\RF24",
   "-IC:\\Users\\5491\\AppData\\Local\\arduino15\\packages\\arduino\\hardware\\avr\\1.8.6\\libraries\\SPI\\src",
   "D:\\workspace\\ArduinoProjects\\weather station\\summer_17_12_21\\weather_Station_without_rf\\output\\sketch\\heater\u0026cooler.ino.cpp",
   "-o",
   "D:\\workspace\\ArduinoProjects\\weather station\\summer_17_12_21\\weather_Station_without_rf\\output\\sketch\\heater\u0026cooler.ino.cpp.o"
  ],
  "file": "D:\\workspace\\ArduinoProjects\\weather station\\summer_17_12_21\\weather_Station_without_rf\\output\\sketch\\heater\u0026cooler.ino.cpp"
 },
 {
  "directory": "d:\\workspace\\ArduinoProjects\\weather station\\summer_17_12_21\\weather_Station_without_rf",
  "arguments": [
   "C:\\Users\\5491\\AppData\\Local\\arduino15\\packages\\arduino\\tools\\avr-gcc\\7.3.0-atmel3.6.1-arduino7/bin/avr-g++",
   "-c",
   "-g",
   "-Os",
   "-w",
   "-std=gnu++11",
   "-fpermissive",
   "-fno-exceptions",
   "-ffunction-sections",
   "-fdata-sections",
   "-fno-threadsafe-statics",
   "-Wno-error=narrowing",
   "-MMD",
   "-flto",
   "-mmcu=atmega328p",
   "-DF_CPU=16000000L",
   "-DARDUINO=10607",
   "-DARDUINO_AVR_NANO",
   "-DARDUINO_ARCH_AVR",
   "-IC:\\Users\\5491\\AppData\\Local\\arduino15\\packages\\arduino\\hardware\\avr\\1.8.6\\cores\\arduino",
   "-IC:\\Users\\5491\\AppData\\Local\\arduino15\\packages\\arduino\\hardware\\avr\\1.8.6\\variants\\eightanaloginputs",
   "-IC:\\Users\\5491\\Documents\\Arduino\\libraries\\ClosedCube_HDC1080\\src",
   "-IC:\\Users\\5491\\Documents\\Arduino\\libraries\\DHT_sensor_library_for_ESPx",
   "-IC:\\Users\\5491\\AppData\\Local\\arduino15\\packages\\arduino\\hardware\\avr\\1.8.6\\libraries\\Wire\\src",
   "-IC:\\Users\\5491\\Documents\\Arduino\\libraries\\DFRobot_SHT20",
   "-IC:\\Users\\5491\\Documents\\Arduino\\libraries\\LiquidCrystal_I2C",
   "-IC:\\Users\\5491\\Documents\\Arduino\\libraries\\RF24",
   "-IC:\\Users\\5491\\AppData\\Local\\arduino15\\packages\\arduino\\hardware\\avr\\1.8.6\\libraries\\SPI\\src",
   "C:\\Users\\5491\\Documents\\Arduino\\libraries\\ClosedCube_HDC1080\\src\\ClosedCube_HDC1080.cpp",
   "-o",
   "D:\\workspace\\ArduinoProjects\\weather station\\summer_17_12_21\\weather_Station_without_rf\\output\\libraries\\ClosedCube_HDC1080\\ClosedCube_HDC1080.cpp.o"
  ],
  "file": "C:\\Users\\5491\\Documents\\Arduino\\libraries\\ClosedCube_HDC1080\\src\\ClosedCube_HDC1080.cpp"
 },
 {
  "directory": "d:\\workspace\\ArduinoProjects\\weather station\\summer_17_12_21\\weather_Station_without_rf",
  "arguments": [
   "C:\\Users\\5491\\AppData\\Local\\arduino15\\packages\\arduino\\tools\\avr-gcc\\7.3.0-atmel3.6.1-arduino7/bin/avr-g++",
   "-c",
   "-g",
   "-Os",
   "-w",
   "-std=gnu++11",
   "-fpermissive",
   "-fno-exceptions",
   "-ffunction-sections",
   "-fdata-sections",
   "-fno-threadsafe-statics",
   "-Wno-error=narrowing",
   "-MMD",
   "-flto",
   "-mmcu=atmega328p",
   "-DF_CPU=16000000L",
   "-DARDUINO=10607",
   "-DARDUINO_AVR_NANO",
   "-DARDUINO_ARCH_AVR",
   "-IC:\\Users\\5491\\AppData\\Local\\arduino15\\packages\\arduino\\hardware\\avr\\1.8.6\\cores\\arduino",
   "-IC:\\Users\\5491\\AppData\\Local\\arduino15\\packages\\arduino\\hardware\\avr\\1.8.6\\variants\\eightanaloginputs",
   "-IC:\\Users\\5491\\Documents\\Arduino\\libraries\\ClosedCube_HDC1080\\src",
   "-IC:\\Users\\5491\\Documents\\Arduino\\libraries\\DHT_sensor_library_for_ESPx",
   "-IC:\\Users\\5491\\AppData\\Local\\arduino15\\packages\\arduino\\hardware\\avr\\1.8.6\\libraries\\Wire\\src",
   "-IC:\\Users\\5491\\Documents\\Arduino\\libraries\\DFRobot_SHT20",
   "-IC:\\Users\\5491\\Documents\\Arduino\\libraries\\LiquidCrystal_I2C",
   "-IC:\\Users\\5491\\Documents\\Arduino\\libraries\\RF24",
   "-IC:\\Users\\5491\\AppData\\Local\\arduino15\\packages\\arduino\\hardware\\avr\\1.8.6\\libraries\\SPI\\src",
   "C:\\Users\\5491\\Documents\\Arduino\\libraries\\DHT_sensor_library_for_ESPx\\DHTesp.cpp",
   "-o",
   "D:\\workspace\\ArduinoProjects\\weather station\\summer_17_12_21\\weather_Station_without_rf\\output\\libraries\\DHT_sensor_library_for_ESPx\\DHTesp.cpp.o"
  ],
  "file": "C:\\Users\\5491\\Documents\\Arduino\\libraries\\DHT_sensor_library_for_ESPx\\DHTesp.cpp"
 },
 {
  "directory": "d:\\workspace\\ArduinoProjects\\weather station\\summer_17_12_21\\weather_Station_without_rf",
  "arguments": [
   "C:\\Users\\5491\\AppData\\Local\\arduino15\\packages\\arduino\\tools\\avr-gcc\\7.3.0-atmel3.6.1-arduino7/bin/avr-g++",
   "-c",
   "-g",
   "-Os",
   "-w",
   "-std=gnu++11",
   "-fpermissive",
   "-fno-exceptions",
   "-ffunction-sections",
   "-fdata-sections",
   "-fno-threadsafe-statics",
   "-Wno-error=narrowing",
   "-MMD",
   "-flto",
   "-mmcu=atmega328p",
   "-DF_CPU=16000000L",
   "-DARDUINO=10607",
   "-DARDUINO_AVR_NANO",
   "-DARDUINO_ARCH_AVR",
   "-IC:\\Users\\5491\\AppData\\Local\\arduino15\\packages\\arduino\\hardware\\avr\\1.8.6\\cores\\arduino",
   "-IC:\\Users\\5491\\AppData\\Local\\arduino15\\packages\\arduino\\hardware\\avr\\1.8.6\\variants\\eightanaloginputs",
   "-IC:\\Users\\5491\\Documents\\Arduino\\libraries\\ClosedCube_HDC1080\\src",
   "-IC:\\Users\\5491\\Documents\\Arduino\\libraries\\DHT_sensor_library_for_ESPx",
   "-IC:\\Users\\5491\\AppData\\Local\\arduino15\\packages\\arduino\\hardware\\avr\\1.8.6\\libraries\\Wire\\src",
   "-IC:\\Users\\5491\\Documents\\Arduino\\libraries\\DFRobot_SHT20",
   "-IC:\\Users\\5491\\Documents\\Arduino\\libraries\\LiquidCrystal_I2C",
   "-IC:\\Users\\5491\\Documents\\Arduino\\libraries\\RF24",
   "-IC:\\Users\\5491\\AppData\\Local\\arduino15\\packages\\arduino\\hardware\\avr\\1.8.6\\libraries\\SPI\\src",
   "C:\\Users\\5491\\AppData\\Local\\arduino15\\packages\\arduino\\hardware\\avr\\1.8.6\\libraries\\Wire\\src\\Wire.cpp",
   "-o",
   "D:\\workspace\\ArduinoProjects\\weather station\\summer_17_12_21\\weather_Station_without_rf\\output\\libraries\\Wire\\Wire.cpp.o"
  ],
  "file": "C:\\Users\\5491\\AppData\\Local\\arduino15\\packages\\arduino\\hardware\\avr\\1.8.6\\libraries\\Wire\\src\\Wire.cpp"
 },
 {
  "directory": "d:\\workspace\\ArduinoProjects\\weather station\\summer_17_12_21\\weather_Station_without_rf",
  "arguments": [
   "C:\\Users\\5491\\AppData\\Local\\arduino15\\packages\\arduino\\tools\\avr-gcc\\7.3.0-atmel3.6.1-arduino7/bin/avr-gcc",
   "-c",
   "-g",
   "-Os",
   "-w",
   "-std=gnu11",
   "-ffunction-sections",
   "-fdata-sections",
   "-MMD",
   "-flto",
   "-fno-fat-lto-objects",
   "-mmcu=atmega328p",
   "-DF_CPU=16000000L",
   "-DARDUINO=10607",
   "-DARDUINO_AVR_NANO",
   "-DARDUINO_ARCH_AVR",
   "-IC:\\Users\\5491\\AppData\\Local\\arduino15\\packages\\arduino\\hardware\\avr\\1.8.6\\cores\\arduino",
   "-IC:\\Users\\5491\\AppData\\Local\\arduino15\\packages\\arduino\\hardware\\avr\\1.8.6\\variants\\eightanaloginputs",
   "-IC:\\Users\\5491\\Documents\\Arduino\\libraries\\ClosedCube_HDC1080\\src",
   "-IC:\\Users\\5491\\Documents\\Arduino\\libraries\\DHT_sensor_library_for_ESPx",
   "-IC:\\Users\\5491\\AppData\\Local\\arduino15\\packages\\arduino\\hardware\\avr\\1.8.6\\libraries\\Wire\\src",
   "-IC:\\Users\\5491\\Documents\\Arduino\\libraries\\DFRobot_SHT20",
   "-IC:\\Users\\5491\\Documents\\Arduino\\libraries\\LiquidCrystal_I2C",
   "-IC:\\Users\\5491\\Documents\\Arduino\\libraries\\RF24",
   "-IC:\\Users\\5491\\AppData\\Local\\arduino15\\packages\\arduino\\hardware\\avr\\1.8.6\\libraries\\SPI\\src",
   "C:\\Users\\5491\\AppData\\Local\\arduino15\\packages\\arduino\\hardware\\avr\\1.8.6\\libraries\\Wire\\src\\utility\\twi.c",
   "-o",
   "D:\\workspace\\ArduinoProjects\\weather station\\summer_17_12_21\\weather_Station_without_rf\\output\\libraries\\Wire\\utility\\twi.c.o"
  ],
  "file": "C:\\Users\\5491\\AppData\\Local\\arduino15\\packages\\arduino\\hardware\\avr\\1.8.6\\libraries\\Wire\\src\\utility\\twi.c"
 },
 {
  "directory": "d:\\workspace\\ArduinoProjects\\weather station\\summer_17_12_21\\weather_Station_without_rf",
  "arguments": [
   "C:\\Users\\5491\\AppData\\Local\\arduino15\\packages\\arduino\\tools\\avr-gcc\\7.3.0-atmel3.6.1-arduino7/bin/avr-g++",
   "-c",
   "-g",
   "-Os",
   "-w",
   "-std=gnu++11",
   "-fpermissive",
   "-fno-exceptions",
   "-ffunction-sections",
   "-fdata-sections",
   "-fno-threadsafe-statics",
   "-Wno-error=narrowing",
   "-MMD",
   "-flto",
   "-mmcu=atmega328p",
   "-DF_CPU=16000000L",
   "-DARDUINO=10607",
   "-DARDUINO_AVR_NANO",
   "-DARDUINO_ARCH_AVR",
   "-IC:\\Users\\5491\\AppData\\Local\\arduino15\\packages\\arduino\\hardware\\avr\\1.8.6\\cores\\arduino",
   "-IC:\\Users\\5491\\AppData\\Local\\arduino15\\packages\\arduino\\hardware\\avr\\1.8.6\\variants\\eightanaloginputs",
   "-IC:\\Users\\5491\\Documents\\Arduino\\libraries\\ClosedCube_HDC1080\\src",
   "-IC:\\Users\\5491\\Documents\\Arduino\\libraries\\DHT_sensor_library_for_ESPx",
   "-IC:\\Users\\5491\\AppData\\Local\\arduino15\\packages\\arduino\\hardware\\avr\\1.8.6\\libraries\\Wire\\src",
   "-IC:\\Users\\5491\\Documents\\Arduino\\libraries\\DFRobot_SHT20",
   "-IC:\\Users\\5491\\Documents\\Arduino\\libraries\\LiquidCrystal_I2C",
   "-IC:\\Users\\5491\\Documents\\Arduino\\libraries\\RF24",
   "-IC:\\Users\\5491\\AppData\\Local\\arduino15\\packages\\arduino\\hardware\\avr\\1.8.6\\libraries\\SPI\\src",
   "C:\\Users\\5491\\Documents\\Arduino\\libraries\\DFRobot_SHT20\\DFRobot_SHT20.cpp",
   "-o",
   "D:\\workspace\\ArduinoProjects\\weather station\\summer_17_12_21\\weather_Station_without_rf\\output\\libraries\\DFRobot_SHT20\\DFRobot_SHT20.cpp.o"
  ],
  "file": "C:\\Users\\5491\\Documents\\Arduino\\libraries\\DFRobot_SHT20\\DFRobot_SHT20.cpp"
 },
 {
  "directory": "d:\\workspace\\ArduinoProjects\\weather station\\summer_17_12_21\\weather_Station_without_rf",
  "arguments": [
   "C:\\Users\\5491\\AppData\\Local\\arduino15\\packages\\arduino\\tools\\avr-gcc\\7.3.0-atmel3.6.1-arduino7/bin/avr-g++",
   "-c",
   "-g",
   "-Os",
   "-w",
   "-std=gnu++11",
   "-fpermissive",
   "-fno-exceptions",
   "-ffunction-sections",
   "-fdata-sections",
   "-fno-threadsafe-statics",
   "-Wno-error=narrowing",
   "-MMD",
   "-flto",
   "-mmcu=atmega328p",
   "-DF_CPU=16000000L",
   "-DARDUINO=10607",
   "-DARDUINO_AVR_NANO",
   "-DARDUINO_ARCH_AVR",
   "-IC:\\Users\\5491\\AppData\\Local\\arduino15\\packages\\arduino\\hardware\\avr\\1.8.6\\cores\\arduino",
   "-IC:\\Users\\5491\\AppData\\Local\\arduino15\\packages\\arduino\\hardware\\avr\\1.8.6\\variants\\eightanaloginputs",
   "-IC:\\Users\\5491\\Documents\\Arduino\\libraries\\ClosedCube_HDC1080\\src",
   "-IC:\\Users\\5491\\Documents\\Arduino\\libraries\\DHT_sensor_library_for_ESPx",
   "-IC:\\Users\\5491\\AppData\\Local\\arduino15\\packages\\arduino\\hardware\\avr\\1.8.6\\libraries\\Wire\\src",
   "-IC:\\Users\\5491\\Documents\\Arduino\\libraries\\DFRobot_SHT20",
   "-IC:\\Users\\5491\\Documents\\Arduino\\libraries\\LiquidCrystal_I2C",
   "-IC:\\Users\\5491\\Documents\\Arduino\\libraries\\RF24",
   "-IC:\\Users\\5491\\AppData\\Local\\arduino15\\packages\\arduino\\hardware\\avr\\1.8.6\\libraries\\SPI\\src",
   "C:\\Users\\5491\\Documents\\Arduino\\libraries\\LiquidCrystal_I2C\\LiquidCrystal_I2C.cpp",
   "-o",
   "D:\\workspace\\ArduinoProjects\\weather station\\summer_17_12_21\\weather_Station_without_rf\\output\\libraries\\LiquidCrystal_I2C\\LiquidCrystal_I2C.cpp.o"
  ],
  "file": "C:\\Users\\5491\\Documents\\Arduino\\libraries\\LiquidCrystal_I2C\\LiquidCrystal_I2C.cpp"
 },
 {
  "directory": "d:\\workspace\\ArduinoProjects\\weather station\\summer_17_12_21\\weather_Station_without_rf",
  "arguments": [
   "C:\\Users\\5491\\AppData\\Local\\arduino15\\packages\\arduino\\tools\\avr-gcc\\7.3.0-atmel3.6.1-arduino7/bin/avr-g++",
   "-c",
   "-g",
   "-Os",
   "-w",
   "-std=gnu++11",
   "-fpermissive",
   "-fno-exceptions",
   "-ffunction-sections",
   "-fdata-sections",
   "-fno-threadsafe-statics",
   "-Wno-error=narrowing",
   "-MMD",
   "-flto",
   "-mmcu=atmega328p",
   "-DF_CPU=16000000L",
   "-DARDUINO=10607",
   "-DARDUINO_AVR_NANO",
   "-DARDUINO_ARCH_AVR",
   "-IC:\\Users\\5491\\AppData\\Local\\arduino15\\packages\\arduino\\hardware\\avr\\1.8.6\\cores\\arduino",
   "-IC:\\Users\\5491\\AppData\\Local\\arduino15\\packages\\arduino\\hardware\\avr\\1.8.6\\variants\\eightanaloginputs",
   "-IC:\\Users\\5491\\Documents\\Arduino\\libraries\\ClosedCube_HDC1080\\src",
   "-IC:\\Users\\5491\\Documents\\Arduino\\libraries\\DHT_sensor_library_for_ESPx",
   "-IC:\\Users\\5491\\AppData\\Local\\arduino15\\packages\\arduino\\hardware\\avr\\1.8.6\\libraries\\Wire\\src",
   "-IC:\\Users\\5491\\Documents\\Arduino\\libraries\\DFRobot_SHT20",
   "-IC:\\Users\\5491\\Documents\\Arduino\\libraries\\LiquidCrystal_I2C",
   "-IC:\\Users\\5491\\Documents\\Arduino\\libraries\\RF24",
   "-IC:\\Users\\5491\\AppData\\Local\\arduino15\\packages\\arduino\\hardware\\avr\\1.8.6\\libraries\\SPI\\src",
   "-IC:\\Users\\5491\\Documents\\Arduino\\libraries\\RF24\\utility",
   "C:\\Users\\5491\\Documents\\Arduino\\libraries\\RF24\\RF24.cpp",
   "-o",
   "D:\\workspace\\ArduinoProjects\\weather station\\summer_17_12_21\\weather_Station_without_rf\\output\\libraries\\RF24\\RF24.cpp.o"
  ],
  "file": "C:\\Users\\5491\\Documents\\Arduino\\libraries\\RF24\\RF24.cpp"
 },
 {
  "directory": "d:\\workspace\\ArduinoProjects\\weather station\\summer_17_12_21\\weather_Station_without_rf",
  "arguments": [
   "C:\\Users\\5491\\AppData\\Local\\arduino15\\packages\\arduino\\tools\\avr-gcc\\7.3.0-atmel3.6.1-arduino7/bin/avr-g++",
   "-c",
   "-g",
   "-Os",
   "-w",
   "-std=gnu++11",
   "-fpermissive",
   "-fno-exceptions",
   "-ffunction-sections",
   "-fdata-sections",
   "-fno-threadsafe-statics",
   "-Wno-error=narrowing",
   "-MMD",
   "-flto",
   "-mmcu=atmega328p",
   "-DF_CPU=16000000L",
   "-DARDUINO=10607",
   "-DARDUINO_AVR_NANO",
   "-DARDUINO_ARCH_AVR",
   "-IC:\\Users\\5491\\AppData\\Local\\arduino15\\packages\\arduino\\hardware\\avr\\1.8.6\\cores\\arduino",
   "-IC:\\Users\\5491\\AppData\\Local\\arduino15\\packages\\arduino\\hardware\\avr\\1.8.6\\variants\\eightanaloginputs",
   "-IC:\\Users\\5491\\Documents\\Arduino\\libraries\\ClosedCube_HDC1080\\src",
   "-IC:\\Users\\5491\\Documents\\Arduino\\libraries\\DHT_sensor_library_for_ESPx",
   "-IC:\\Users\\5491\\AppData\\Local\\arduino15\\packages\\arduino\\hardware\\avr\\1.8.6\\libraries\\Wire\\src",
   "-IC:\\Users\\5491\\Documents\\Arduino\\libraries\\DFRobot_SHT20",
   "-IC:\\Users\\5491\\Documents\\Arduino\\libraries\\LiquidCrystal_I2C",
   "-IC:\\Users\\5491\\Documents\\Arduino\\libraries\\RF24",
   "-IC:\\Users\\5491\\AppData\\Local\\arduino15\\packages\\arduino\\hardware\\avr\\1.8.6\\libraries\\SPI\\src",
   "C:\\Users\\5491\\AppData\\Local\\arduino15\\packages\\arduino\\hardware\\avr\\1.8.6\\libraries\\SPI\\src\\SPI.cpp",
   "-o",
   "D:\\workspace\\ArduinoProjects\\weather station\\summer_17_12_21\\weather_Station_without_rf\\output\\libraries\\SPI\\SPI.cpp.o"
  ],
  "file": "C:\\Users\\5491\\AppData\\Local\\arduino15\\packages\\arduino\\hardware\\avr\\1.8.6\\libraries\\SPI\\src\\SPI.cpp"
 },
 {
  "directory": "d:\\workspace\\ArduinoProjects\\weather station\\summer_17_12_21\\weather_Station_without_rf",
  "arguments": [
   "C:\\Users\\5491\\AppData\\Local\\arduino15\\packages\\arduino\\tools\\avr-gcc\\7.3.0-atmel3.6.1-arduino7/bin/avr-g++",
   "-c",
   "-g",
   "-Os",
   "-w",
   "-std=gnu++11",
   "-fpermissive",
   "-fno-exceptions",
   "-ffunction-sections",
   "-fdata-sections",
   "-fno-threadsafe-statics",
   "-Wno-error=narrowing",
   "-MMD",
   "-flto",
   "-mmcu=atmega328p",
   "-DF_CPU=16000000L",
   "-DARDUINO=10607",
   "-DARDUINO_AVR_NANO",
   "-DARDUINO_ARCH_AVR",
   "-IC:\\Users\\5491\\AppData\\Local\\arduino15\\packages\\arduino\\hardware\\avr\\1.8.6\\cores\\arduino",
   "-IC:\\Users\\5491\\AppData\\Local\\arduino15\\packages\\arduino\\hardware\\avr\\1.8.6\\variants\\eightanaloginputs",
   "C:\\Users\\5491\\AppData\\Local\\arduino15\\packages\\arduino\\hardware\\avr\\1.8.6\\cores\\arduino\\CDC.cpp",
   "-o",
   "D:\\workspace\\ArduinoProjects\\weather station\\summer_17_12_21\\weather_Station_without_rf\\output\\core\\CDC.cpp.o"
  ],
  "file": "C:\\Users\\5491\\AppData\\Local\\arduino15\\packages\\arduino\\hardware\\avr\\1.8.6\\cores\\arduino\\CDC.cpp"
 },
 {
  "directory": "d:\\workspace\\ArduinoProjects\\weather station\\summer_17_12_21\\weather_Station_without_rf",
  "arguments": [
   "C:\\Users\\5491\\AppData\\Local\\arduino15\\packages\\arduino\\tools\\avr-gcc\\7.3.0-atmel3.6.1-arduino7/bin/avr-g++",
   "-c",
   "-g",
   "-Os",
   "-w",
   "-std=gnu++11",
   "-fpermissive",
   "-fno-exceptions",
   "-ffunction-sections",
   "-fdata-sections",
   "-fno-threadsafe-statics",
   "-Wno-error=narrowing",
   "-MMD",
   "-flto",
   "-mmcu=atmega328p",
   "-DF_CPU=16000000L",
   "-DARDUINO=10607",
   "-DARDUINO_AVR_NANO",
   "-DARDUINO_ARCH_AVR",
   "-IC:\\Users\\5491\\AppData\\Local\\arduino15\\packages\\arduino\\hardware\\avr\\1.8.6\\cores\\arduino",
   "-IC:\\Users\\5491\\AppData\\Local\\arduino15\\packages\\arduino\\hardware\\avr\\1.8.6\\variants\\eightanaloginputs",
   "C:\\Users\\5491\\AppData\\Local\\arduino15\\packages\\arduino\\hardware\\avr\\1.8.6\\cores\\arduino\\HardwareSerial3.cpp",
   "-o",
   "D:\\workspace\\ArduinoProjects\\weather station\\summer_17_12_21\\weather_Station_without_rf\\output\\core\\HardwareSerial3.cpp.o"
  ],
  "file": "C:\\Users\\5491\\AppData\\Local\\arduino15\\packages\\arduino\\hardware\\avr\\1.8.6\\cores\\arduino\\HardwareSerial3.cpp"
 },
 {
  "directory": "d:\\workspace\\ArduinoProjects\\weather station\\summer_17_12_21\\weather_Station_without_rf",
  "arguments": [
   "C:\\Users\\5491\\AppData\\Local\\arduino15\\packages\\arduino\\tools\\avr-gcc\\7.3.0-atmel3.6.1-arduino7/bin/avr-g++",
   "-c",
   "-g",
   "-Os",
   "-w",
   "-std=gnu++11",
   "-fpermissive",
   "-fno-exceptions",
   "-ffunction-sections",
   "-fdata-sections",
   "-fno-threadsafe-statics",
   "-Wno-error=narrowing",
   "-MMD",
   "-flto",
   "-mmcu=atmega328p",
   "-DF_CPU=16000000L",
   "-DARDUINO=10607",
   "-DARDUINO_AVR_NANO",
   "-DARDUINO_ARCH_AVR",
   "-IC:\\Users\\5491\\AppData\\Local\\arduino15\\packages\\arduino\\hardware\\avr\\1.8.6\\cores\\arduino",
   "-IC:\\Users\\5491\\AppData\\Local\\arduino15\\packages\\arduino\\hardware\\avr\\1.8.6\\variants\\eightanaloginputs",
   "C:\\Users\\5491\\AppData\\Local\\arduino15\\packages\\arduino\\hardware\\avr\\1.8.6\\cores\\arduino\\PluggableUSB.cpp",
   "-o",
   "D:\\workspace\\ArduinoProjects\\weather station\\summer_17_12_21\\weather_Station_without_rf\\output\\core\\PluggableUSB.cpp.o"
  ],
  "file": "C:\\Users\\5491\\AppData\\Local\\arduino15\\packages\\arduino\\hardware\\avr\\1.8.6\\cores\\arduino\\PluggableUSB.cpp"
 },
 {
  "directory": "d:\\workspace\\ArduinoProjects\\weather station\\summer_17_12_21\\weather_Station_without_rf",
  "arguments": [
   "C:\\Users\\5491\\AppData\\Local\\arduino15\\packages\\arduino\\tools\\avr-gcc\\7.3.0-atmel3.6.1-arduino7/bin/avr-g++",
   "-c",
   "-g",
   "-Os",
   "-w",
   "-std=gnu++11",
   "-fpermissive",
   "-fno-exceptions",
   "-ffunction-sections",
   "-fdata-sections",
   "-fno-threadsafe-statics",
   "-Wno-error=narrowing",
   "-MMD",
   "-flto",
   "-mmcu=atmega328p",
   "-DF_CPU=16000000L",
   "-DARDUINO=10607",
   "-DARDUINO_AVR_NANO",
   "-DARDUINO_ARCH_AVR",
   "-IC:\\Users\\5491\\AppData\\Local\\arduino15\\packages\\arduino\\hardware\\avr\\1.8.6\\cores\\arduino",
   "-IC:\\Users\\5491\\AppData\\Local\\arduino15\\packages\\arduino\\hardware\\avr\\1.8.6\\variants\\eightanaloginputs",
   "C:\\Users\\5491\\AppData\\Local\\arduino15\\packages\\arduino\\hardware\\avr\\1.8.6\\cores\\arduino\\IPAddress.cpp",
   "-o",
   "D:\\workspace\\ArduinoProjects\\weather station\\summer_17_12_21\\weather_Station_without_rf\\output\\core\\IPAddress.cpp.o"
  ],
  "file": "C:\\Users\\5491\\AppData\\Local\\arduino15\\packages\\arduino\\hardware\\avr\\1.8.6\\cores\\arduino\\IPAddress.cpp"
 },
 {
  "directory": "d:\\workspace\\ArduinoProjects\\weather station\\summer_17_12_21\\weather_Station_without_rf",
  "arguments": [
   "C:\\Users\\5491\\AppData\\Local\\arduino15\\packages\\arduino\\tools\\avr-gcc\\7.3.0-atmel3.6.1-arduino7/bin/avr-g++",
   "-c",
   "-g",
   "-Os",
   "-w",
   "-std=gnu++11",
   "-fpermissive",
   "-fno-exceptions",
   "-ffunction-sections",
   "-fdata-sections",
   "-fno-threadsafe-statics",
   "-Wno-error=narrowing",
   "-MMD",
   "-flto",
   "-mmcu=atmega328p",
   "-DF_CPU=16000000L",
   "-DARDUINO=10607",
   "-DARDUINO_AVR_NANO",
   "-DARDUINO_ARCH_AVR",
   "-IC:\\Users\\5491\\AppData\\Local\\arduino15\\packages\\arduino\\hardware\\avr\\1.8.6\\cores\\arduino",
   "-IC:\\Users\\5491\\AppData\\Local\\arduino15\\packages\\arduino\\hardware\\avr\\1.8.6\\variants\\eightanaloginputs",
   "C:\\Users\\5491\\AppData\\Local\\arduino15\\packages\\arduino\\hardware\\avr\\1.8.6\\cores\\arduino\\HardwareSerial0.cpp",
   "-o",
   "D:\\workspace\\ArduinoProjects\\weather station\\summer_17_12_21\\weather_Station_without_rf\\output\\core\\HardwareSerial0.cpp.o"
  ],
  "file": "C:\\Users\\5491\\AppData\\Local\\arduino15\\packages\\arduino\\hardware\\avr\\1.8.6\\cores\\arduino\\HardwareSerial0.cpp"
 },
 {
  "directory": "d:\\workspace\\ArduinoProjects\\weather station\\summer_17_12_21\\weather_Station_without_rf",
  "arguments": [
   "C:\\Users\\5491\\AppData\\Local\\arduino15\\packages\\arduino\\tools\\avr-gcc\\7.3.0-atmel3.6.1-arduino7/bin/avr-g++",
   "-c",
   "-g",
   "-Os",
   "-w",
   "-std=gnu++11",
   "-fpermissive",
   "-fno-exceptions",
   "-ffunction-sections",
   "-fdata-sections",
   "-fno-threadsafe-statics",
   "-Wno-error=narrowing",
   "-MMD",
   "-flto",
   "-mmcu=atmega328p",
   "-DF_CPU=16000000L",
   "-DARDUINO=10607",
   "-DARDUINO_AVR_NANO",
   "-DARDUINO_ARCH_AVR",
   "-IC:\\Users\\5491\\AppData\\Local\\arduino15\\packages\\arduino\\hardware\\avr\\1.8.6\\cores\\arduino",
   "-IC:\\Users\\5491\\AppData\\Local\\arduino15\\packages\\arduino\\hardware\\avr\\1.8.6\\variants\\eightanaloginputs",
   "C:\\Users\\5491\\AppData\\Local\\arduino15\\packages\\arduino\\hardware\\avr\\1.8.6\\cores\\arduino\\HardwareSerial1.cpp",
   "-o",
   "D:\\workspace\\ArduinoProjects\\weather station\\summer_17_12_21\\weather_Station_without_rf\\output\\core\\HardwareSerial1.cpp.o"
  ],
  "file": "C:\\Users\\5491\\AppData\\Local\\arduino15\\packages\\arduino\\hardware\\avr\\1.8.6\\cores\\arduino\\HardwareSerial1.cpp"
 },
 {
  "directory": "d:\\workspace\\ArduinoProjects\\weather station\\summer_17_12_21\\weather_Station_without_rf",
  "arguments": [
   "C:\\Users\\5491\\AppData\\Local\\arduino15\\packages\\arduino\\tools\\avr-gcc\\7.3.0-atmel3.6.1-arduino7/bin/avr-g++",
   "-c",
   "-g",
   "-Os",
   "-w",
   "-std=gnu++11",
   "-fpermissive",
   "-fno-exceptions",
   "-ffunction-sections",
   "-fdata-sections",
   "-fno-threadsafe-statics",
   "-Wno-error=narrowing",
   "-MMD",
   "-flto",
   "-mmcu=atmega328p",
   "-DF_CPU=16000000L",
   "-DARDUINO=10607",
   "-DARDUINO_AVR_NANO",
   "-DARDUINO_ARCH_AVR",
   "-IC:\\Users\\5491\\AppData\\Local\\arduino15\\packages\\arduino\\hardware\\avr\\1.8.6\\cores\\arduino",
   "-IC:\\Users\\5491\\AppData\\Local\\arduino15\\packages\\arduino\\hardware\\avr\\1.8.6\\variants\\eightanaloginputs",
   "C:\\Users\\5491\\AppData\\Local\\arduino15\\packages\\arduino\\hardware\\avr\\1.8.6\\cores\\arduino\\HardwareSerial.cpp",
   "-o",
   "D:\\workspace\\ArduinoProjects\\weather station\\summer_17_12_21\\weather_Station_without_rf\\output\\core\\HardwareSerial.cpp.o"
  ],
  "file": "C:\\Users\\5491\\AppData\\Local\\arduino15\\packages\\arduino\\hardware\\avr\\1.8.6\\cores\\arduino\\HardwareSerial.cpp"
 },
 {
  "directory": "d:\\workspace\\ArduinoProjects\\weather station\\summer_17_12_21\\weather_Station_without_rf",
  "arguments": [
   "C:\\Users\\5491\\AppData\\Local\\arduino15\\packages\\arduino\\tools\\avr-gcc\\7.3.0-atmel3.6.1-arduino7/bin/avr-g++",
   "-c",
   "-g",
   "-Os",
   "-w",
   "-std=gnu++11",
   "-fpermissive",
   "-fno-exceptions",
   "-ffunction-sections",
   "-fdata-sections",
   "-fno-threadsafe-statics",
   "-Wno-error=narrowing",
   "-MMD",
   "-flto",
   "-mmcu=atmega328p",
   "-DF_CPU=16000000L",
   "-DARDUINO=10607",
   "-DARDUINO_AVR_NANO",
   "-DARDUINO_ARCH_AVR",
   "-IC:\\Users\\5491\\AppData\\Local\\arduino15\\packages\\arduino\\hardware\\avr\\1.8.6\\cores\\arduino",
   "-IC:\\Users\\5491\\AppData\\Local\\arduino15\\packages\\arduino\\hardware\\avr\\1.8.6\\variants\\eightanaloginputs",
   "C:\\Users\\5491\\AppData\\Local\\arduino15\\packages\\arduino\\hardware\\avr\\1.8.6\\cores\\arduino\\HardwareSerial2.cpp",
   "-o",
   "D:\\workspace\\ArduinoProjects\\weather station\\summer_17_12_21\\weather_Station_without_rf\\output\\core\\HardwareSerial2.cpp.o"
  ],
  "file": "C:\\Users\\5491\\AppData\\Local\\arduino15\\packages\\arduino\\hardware\\avr\\1.8.6\\cores\\arduino\\HardwareSerial2.cpp"
 },
 {
  "directory": "d:\\workspace\\ArduinoProjects\\weather station\\summer_17_12_21\\weather_Station_without_rf",
  "arguments": [
   "C:\\Users\\5491\\AppData\\Local\\arduino15\\packages\\arduino\\tools\\avr-gcc\\7.3.0-atmel3.6.1-arduino7/bin/avr-g++",
   "-c",
   "-g",
   "-Os",
   "-w",
   "-std=gnu++11",
   "-fpermissive",
   "-fno-exceptions",
   "-ffunction-sections",
   "-fdata-sections",
   "-fno-threadsafe-statics",
   "-Wno-error=narrowing",
   "-MMD",
   "-flto",
   "-mmcu=atmega328p",
   "-DF_CPU=16000000L",
   "-DARDUINO=10607",
   "-DARDUINO_AVR_NANO",
   "-DARDUINO_ARCH_AVR",
   "-IC:\\Users\\5491\\AppData\\Local\\arduino15\\packages\\arduino\\hardware\\avr\\1.8.6\\cores\\arduino",
   "-IC:\\Users\\5491\\AppData\\Local\\arduino15\\packages\\arduino\\hardware\\avr\\1.8.6\\variants\\eightanaloginputs",
   "C:\\Users\\5491\\AppData\\Local\\arduino15\\packages\\arduino\\hardware\\avr\\1.8.6\\cores\\arduino\\Print.cpp",
   "-o",
   "D:\\workspace\\ArduinoProjects\\weather station\\summer_17_12_21\\weather_Station_without_rf\\output\\core\\Print.cpp.o"
  ],
  "file": "C:\\Users\\5491\\AppData\\Local\\arduino15\\packages\\arduino\\hardware\\avr\\1.8.6\\cores\\arduino\\Print.cpp"
 },
 {
  "directory": "d:\\workspace\\ArduinoProjects\\weather station\\summer_17_12_21\\weather_Station_without_rf",
  "arguments": [
   "C:\\Users\\5491\\AppData\\Local\\arduino15\\packages\\arduino\\tools\\avr-gcc\\7.3.0-atmel3.6.1-arduino7/bin/avr-g++",
   "-c",
   "-g",
   "-Os",
   "-w",
   "-std=gnu++11",
   "-fpermissive",
   "-fno-exceptions",
   "-ffunction-sections",
   "-fdata-sections",
   "-fno-threadsafe-statics",
   "-Wno-error=narrowing",
   "-MMD",
   "-flto",
   "-mmcu=atmega328p",
   "-DF_CPU=16000000L",
   "-DARDUINO=10607",
   "-DARDUINO_AVR_NANO",
   "-DARDUINO_ARCH_AVR",
   "-IC:\\Users\\5491\\AppData\\Local\\arduino15\\packages\\arduino\\hardware\\avr\\1.8.6\\cores\\arduino",
   "-IC:\\Users\\5491\\AppData\\Local\\arduino15\\packages\\arduino\\hardware\\avr\\1.8.6\\variants\\eightanaloginputs",
   "C:\\Users\\5491\\AppData\\Local\\arduino15\\packages\\arduino\\hardware\\avr\\1.8.6\\cores\\arduino\\Tone.cpp",
   "-o",
   "D:\\workspace\\ArduinoProjects\\weather station\\summer_17_12_21\\weather_Station_without_rf\\output\\core\\Tone.cpp.o"
  ],
  "file": "C:\\Users\\5491\\AppData\\Local\\arduino15\\packages\\arduino\\hardware\\avr\\1.8.6\\cores\\arduino\\Tone.cpp"
 },
 {
  "directory": "d:\\workspace\\ArduinoProjects\\weather station\\summer_17_12_21\\weather_Station_without_rf",
  "arguments": [
   "C:\\Users\\5491\\AppData\\Local\\arduino15\\packages\\arduino\\tools\\avr-gcc\\7.3.0-atmel3.6.1-arduino7/bin/avr-g++",
   "-c",
   "-g",
   "-Os",
   "-w",
   "-std=gnu++11",
   "-fpermissive",
   "-fno-exceptions",
   "-ffunction-sections",
   "-fdata-sections",
   "-fno-threadsafe-statics",
   "-Wno-error=narrowing",
   "-MMD",
   "-flto",
   "-mmcu=atmega328p",
   "-DF_CPU=16000000L",
   "-DARDUINO=10607",
   "-DARDUINO_AVR_NANO",
   "-DARDUINO_ARCH_AVR",
   "-IC:\\Users\\5491\\AppData\\Local\\arduino15\\packages\\arduino\\hardware\\avr\\1.8.6\\cores\\arduino",
   "-IC:\\Users\\5491\\AppData\\Local\\arduino15\\packages\\arduino\\hardware\\avr\\1.8.6\\variants\\eightanaloginputs",
   "C:\\Users\\5491\\AppData\\Local\\arduino15\\packages\\arduino\\hardware\\avr\\1.8.6\\cores\\arduino\\Stream.cpp",
   "-o",
   "D:\\workspace\\ArduinoProjects\\weather station\\summer_17_12_21\\weather_Station_without_rf\\output\\core\\Stream.cpp.o"
  ],
  "file": "C:\\Users\\5491\\AppData\\Local\\arduino15\\packages\\arduino\\hardware\\avr\\1.8.6\\cores\\arduino\\Stream.cpp"
 },
 {
  "directory": "d:\\workspace\\ArduinoProjects\\weather station\\summer_17_12_21\\weather_Station_without_rf",
  "arguments": [
   "C:\\Users\\5491\\AppData\\Local\\arduino15\\packages\\arduino\\tools\\avr-gcc\\7.3.0-atmel3.6.1-arduino7/bin/avr-gcc",
   "-c",
   "-g",
   "-Os",
   "-w",
   "-std=gnu11",
   "-ffunction-sections",
   "-fdata-sections",
   "-MMD",
   "-flto",
   "-fno-fat-lto-objects",
   "-mmcu=atmega328p",
   "-DF_CPU=16000000L",
   "-DARDUINO=10607",
   "-DARDUINO_AVR_NANO",
   "-DARDUINO_ARCH_AVR",
   "-IC:\\Users\\5491\\AppData\\Local\\arduino15\\packages\\arduino\\hardware\\avr\\1.8.6\\cores\\arduino",
   "-IC:\\Users\\5491\\AppData\\Local\\arduino15\\packages\\arduino\\hardware\\avr\\1.8.6\\variants\\eightanaloginputs",
   "C:\\Users\\5491\\AppData\\Local\\arduino15\\packages\\arduino\\hardware\\avr\\1.8.6\\cores\\arduino\\WInterrupts.c",
   "-o",
   "D:\\workspace\\ArduinoProjects\\weather station\\summer_17_12_21\\weather_Station_without_rf\\output\\core\\WInterrupts.c.o"
  ],
  "file": "C:\\Users\\5491\\AppData\\Local\\arduino15\\packages\\arduino\\hardware\\avr\\1.8.6\\cores\\arduino\\WInterrupts.c"
 },
 {
  "directory": "d:\\workspace\\ArduinoProjects\\weather station\\summer_17_12_21\\weather_Station_without_rf",
  "arguments": [
   "C:\\Users\\5491\\AppData\\Local\\arduino15\\packages\\arduino\\tools\\avr-gcc\\7.3.0-atmel3.6.1-arduino7/bin/avr-g++",
   "-c",
   "-g",
   "-Os",
   "-w",
   "-std=gnu++11",
   "-fpermissive",
   "-fno-exceptions",
   "-ffunction-sections",
   "-fdata-sections",
   "-fno-threadsafe-statics",
   "-Wno-error=narrowing",
   "-MMD",
   "-flto",
   "-mmcu=atmega328p",
   "-DF_CPU=16000000L",
   "-DARDUINO=10607",
   "-DARDUINO_AVR_NANO",
   "-DARDUINO_ARCH_AVR",
   "-IC:\\Users\\5491\\AppData\\Local\\arduino15\\packages\\arduino\\hardware\\avr\\1.8.6\\cores\\arduino",
   "-IC:\\Users\\5491\\AppData\\Local\\arduino15\\packages\\arduino\\hardware\\avr\\1.8.6\\variants\\eightanaloginputs",
   "C:\\Users\\5491\\AppData\\Local\\arduino15\\packages\\arduino\\hardware\\avr\\1.8.6\\cores\\arduino\\USBCore.cpp",
   "-o",
   "D:\\workspace\\ArduinoProjects\\weather station\\summer_17_12_21\\weather_Station_without_rf\\output\\core\\USBCore.cpp.o"
  ],
  "file": "C:\\Users\\5491\\AppData\\Local\\arduino15\\packages\\arduino\\hardware\\avr\\1.8.6\\cores\\arduino\\USBCore.cpp"
 },
 {
  "directory": "d:\\workspace\\ArduinoProjects\\weather station\\summer_17_12_21\\weather_Station_without_rf",
  "arguments": [
   "C:\\Users\\5491\\AppData\\Local\\arduino15\\packages\\arduino\\tools\\avr-gcc\\7.3.0-atmel3.6.1-arduino7/bin/avr-g++",
   "-c",
   "-g",
   "-Os",
   "-w",
   "-std=gnu++11",
   "-fpermissive",
   "-fno-exceptions",
   "-ffunction-sections",
   "-fdata-sections",
   "-fno-threadsafe-statics",
   "-Wno-error=narrowing",
   "-MMD",
   "-flto",
   "-mmcu=atmega328p",
   "-DF_CPU=16000000L",
   "-DARDUINO=10607",
   "-DARDUINO_AVR_NANO",
   "-DARDUINO_ARCH_AVR",
   "-IC:\\Users\\5491\\AppData\\Local\\arduino15\\packages\\arduino\\hardware\\avr\\1.8.6\\cores\\arduino",
   "-IC:\\Users\\5491\\AppData\\Local\\arduino15\\packages\\arduino\\hardware\\avr\\1.8.6\\variants\\eightanaloginputs",
   "C:\\Users\\5491\\AppData\\Local\\arduino15\\packages\\arduino\\hardware\\avr\\1.8.6\\cores\\arduino\\WString.cpp",
   "-o",
   "D:\\workspace\\ArduinoProjects\\weather station\\summer_17_12_21\\weather_Station_without_rf\\output\\core\\WString.cpp.o"
  ],
  "file": "C:\\Users\\5491\\AppData\\Local\\arduino15\\packages\\arduino\\hardware\\avr\\1.8.6\\cores\\arduino\\WString.cpp"
 },
 {
  "directory": "d:\\workspace\\ArduinoProjects\\weather station\\summer_17_12_21\\weather_Station_without_rf",
  "arguments": [
   "C:\\Users\\5491\\AppData\\Local\\arduino15\\packages\\arduino\\tools\\avr-gcc\\7.3.0-atmel3.6.1-arduino7/bin/avr-g++",
   "-c",
   "-g",
   "-Os",
   "-w",
   "-std=gnu++11",
   "-fpermissive",
   "-fno-exceptions",
   "-ffunction-sections",
   "-fdata-sections",
   "-fno-threadsafe-statics",
   "-Wno-error=narrowing",
   "-MMD",
   "-flto",
   "-mmcu=atmega328p",
   "-DF_CPU=16000000L",
   "-DARDUINO=10607",
   "-DARDUINO_AVR_NANO",
   "-DARDUINO_ARCH_AVR",
   "-IC:\\Users\\5491\\AppData\\Local\\arduino15\\packages\\arduino\\hardware\\avr\\1.8.6\\cores\\arduino",
   "-IC:\\Users\\5491\\AppData\\Local\\arduino15\\packages\\arduino\\hardware\\avr\\1.8.6\\variants\\eightanaloginputs",
   "C:\\Users\\5491\\AppData\\Local\\arduino15\\packages\\arduino\\hardware\\avr\\1.8.6\\cores\\arduino\\abi.cpp",
   "-o",
   "D:\\workspace\\ArduinoProjects\\weather station\\summer_17_12_21\\weather_Station_without_rf\\output\\core\\abi.cpp.o"
  ],
  "file": "C:\\Users\\5491\\AppData\\Local\\arduino15\\packages\\arduino\\hardware\\avr\\1.8.6\\cores\\arduino\\abi.cpp"
 },
 {
  "directory": "d:\\workspace\\ArduinoProjects\\weather station\\summer_17_12_21\\weather_Station_without_rf",
  "arguments": [
   "C:\\Users\\5491\\AppData\\Local\\arduino15\\packages\\arduino\\tools\\avr-gcc\\7.3.0-atmel3.6.1-arduino7/bin/avr-g++",
   "-c",
   "-g",
   "-Os",
   "-w",
   "-std=gnu++11",
   "-fpermissive",
   "-fno-exceptions",
   "-ffunction-sections",
   "-fdata-sections",
   "-fno-threadsafe-statics",
   "-Wno-error=narrowing",
   "-MMD",
   "-flto",
   "-mmcu=atmega328p",
   "-DF_CPU=16000000L",
   "-DARDUINO=10607",
   "-DARDUINO_AVR_NANO",
   "-DARDUINO_ARCH_AVR",
   "-IC:\\Users\\5491\\AppData\\Local\\arduino15\\packages\\arduino\\hardware\\avr\\1.8.6\\cores\\arduino",
   "-IC:\\Users\\5491\\AppData\\Local\\arduino15\\packages\\arduino\\hardware\\avr\\1.8.6\\variants\\eightanaloginputs",
   "C:\\Users\\5491\\AppData\\Local\\arduino15\\packages\\arduino\\hardware\\avr\\1.8.6\\cores\\arduino\\WMath.cpp",
   "-o",
   "D:\\workspace\\ArduinoProjects\\weather station\\summer_17_12_21\\weather_Station_without_rf\\output\\core\\WMath.cpp.o"
  ],
  "file": "C:\\Users\\5491\\AppData\\Local\\arduino15\\packages\\arduino\\hardware\\avr\\1.8.6\\cores\\arduino\\WMath.cpp"
 },
 {
  "directory": "d:\\workspace\\ArduinoProjects\\weather station\\summer_17_12_21\\weather_Station_without_rf",
  "arguments": [
   "C:\\Users\\5491\\AppData\\Local\\arduino15\\packages\\arduino\\tools\\avr-gcc\\7.3.0-atmel3.6.1-arduino7/bin/avr-g++",
   "-c",
   "-g",
   "-Os",
   "-w",
   "-std=gnu++11",
   "-fpermissive",
   "-fno-exceptions",
   "-ffunction-sections",
   "-fdata-sections",
   "-fno-threadsafe-statics",
   "-Wno-error=narrowing",
   "-MMD",
   "-flto",
   "-mmcu=atmega328p",
   "-DF_CPU=16000000L",
   "-DARDUINO=10607",
   "-DARDUINO_AVR_NANO",
   "-DARDUINO_ARCH_AVR",
   "-IC:\\Users\\5491\\AppData\\Local\\arduino15\\packages\\arduino\\hardware\\avr\\1.8.6\\cores\\arduino",
   "-IC:\\Users\\5491\\AppData\\Local\\arduino15\\packages\\arduino\\hardware\\avr\\1.8.6\\variants\\eightanaloginputs",
   "C:\\Users\\5491\\AppData\\Local\\arduino15\\packages\\arduino\\hardware\\avr\\1.8.6\\cores\\arduino\\new.cpp",
   "-o",
   "D:\\workspace\\ArduinoProjects\\weather station\\summer_17_12_21\\weather_Station_without_rf\\output\\core\\new.cpp.o"
  ],
  "file": "C:\\Users\\5491\\AppData\\Local\\arduino15\\packages\\arduino\\hardware\\avr\\1.8.6\\cores\\arduino\\new.cpp"
 },
 {
  "directory": "d:\\workspace\\ArduinoProjects\\weather station\\summer_17_12_21\\weather_Station_without_rf",
  "arguments": [
   "C:\\Users\\5491\\AppData\\Local\\arduino15\\packages\\arduino\\tools\\avr-gcc\\7.3.0-atmel3.6.1-arduino7/bin/avr-gcc",
   "-c",
   "-g",
   "-Os",
   "-w",
   "-std=gnu11",
   "-ffunction-sections",
   "-fdata-sections",
   "-MMD",
   "-flto",
   "-fno-fat-lto-objects",
   "-mmcu=atmega328p",
   "-DF_CPU=16000000L",
   "-DARDUINO=10607",
   "-DARDUINO_AVR_NANO",
   "-DARDUINO_ARCH_AVR",
   "-IC:\\Users\\5491\\AppData\\Local\\arduino15\\packages\\arduino\\hardware\\avr\\1.8.6\\cores\\arduino",
   "-IC:\\Users\\5491\\AppData\\Local\\arduino15\\packages\\arduino\\hardware\\avr\\1.8.6\\variants\\eightanaloginputs",
   "C:\\Users\\5491\\AppData\\Local\\arduino15\\packages\\arduino\\hardware\\avr\\1.8.6\\cores\\arduino\\hooks.c",
   "-o",
   "D:\\workspace\\ArduinoProjects\\weather station\\summer_17_12_21\\weather_Station_without_rf\\output\\core\\hooks.c.o"
  ],
  "file": "C:\\Users\\5491\\AppData\\Local\\arduino15\\packages\\arduino\\hardware\\avr\\1.8.6\\cores\\arduino\\hooks.c"
 },
 {
  "directory": "d:\\workspace\\ArduinoProjects\\weather station\\summer_17_12_21\\weather_Station_without_rf",
  "arguments": [
   "C:\\Users\\5491\\AppData\\Local\\arduino15\\packages\\arduino\\tools\\avr-gcc\\7.3.0-atmel3.6.1-arduino7/bin/avr-g++",
   "-c",
   "-g",
   "-Os",
   "-w",
   "-std=gnu++11",
   "-fpermissive",
   "-fno-exceptions",
   "-ffunction-sections",
   "-fdata-sections",
   "-fno-threadsafe-statics",
   "-Wno-error=narrowing",
   "-MMD",
   "-flto",
   "-mmcu=atmega328p",
   "-DF_CPU=16000000L",
   "-DARDUINO=10607",
   "-DARDUINO_AVR_NANO",
   "-DARDUINO_ARCH_AVR",
   "-IC:\\Users\\5491\\AppData\\Local\\arduino15\\packages\\arduino\\hardware\\avr\\1.8.6\\cores\\arduino",
   "-IC:\\Users\\5491\\AppData\\Local\\arduino15\\packages\\arduino\\hardware\\avr\\1.8.6\\variants\\eightanaloginputs",
   "C:\\Users\\5491\\AppData\\Local\\arduino15\\packages\\arduino\\hardware\\avr\\1.8.6\\cores\\arduino\\main.cpp",
   "-o",
   "D:\\workspace\\ArduinoProjects\\weather station\\summer_17_12_21\\weather_Station_without_rf\\output\\core\\main.cpp.o"
  ],
  "file": "C:\\Users\\5491\\AppData\\Local\\arduino15\\packages\\arduino\\hardware\\avr\\1.8.6\\cores\\arduino\\main.cpp"
 },
 {
  "directory": "d:\\workspace\\ArduinoProjects\\weather station\\summer_17_12_21\\weather_Station_without_rf",
  "arguments": [
   "C:\\Users\\5491\\AppData\\Local\\arduino15\\packages\\arduino\\tools\\avr-gcc\\7.3.0-atmel3.6.1-arduino7/bin/avr-gcc",
   "-c",
   "-g",
   "-x",
   "assembler-with-cpp",
   "-flto",
   "-MMD",
   "-mmcu=atmega328p",
   "-DF_CPU=16000000L",
   "-DARDUINO=10607",
   "-DARDUINO_AVR_NANO",
   "-DARDUINO_ARCH_AVR",
   "-IC:\\Users\\5491\\AppData\\Local\\arduino15\\packages\\arduino\\hardware\\avr\\1.8.6\\cores\\arduino",
   "-IC:\\Users\\5491\\AppData\\Local\\arduino15\\packages\\arduino\\hardware\\avr\\1.8.6\\variants\\eightanaloginputs",
   "C:\\Users\\5491\\AppData\\Local\\arduino15\\packages\\arduino\\hardware\\avr\\1.8.6\\cores\\arduino\\wiring_pulse.S",
   "-o",
   "D:\\workspace\\ArduinoProjects\\weather station\\summer_17_12_21\\weather_Station_without_rf\\output\\core\\wiring_pulse.S.o"
  ],
  "file": "C:\\Users\\5491\\AppData\\Local\\arduino15\\packages\\arduino\\hardware\\avr\\1.8.6\\cores\\arduino\\wiring_pulse.S"
 },
 {
  "directory": "d:\\workspace\\ArduinoProjects\\weather station\\summer_17_12_21\\weather_Station_without_rf",
  "arguments": [
   "C:\\Users\\5491\\AppData\\Local\\arduino15\\packages\\arduino\\tools\\avr-gcc\\7.3.0-atmel3.6.1-arduino7/bin/avr-gcc",
   "-c",
   "-g",
   "-Os",
   "-w",
   "-std=gnu11",
   "-ffunction-sections",
   "-fdata-sections",
   "-MMD",
   "-flto",
   "-fno-fat-lto-objects",
   "-mmcu=atmega328p",
   "-DF_CPU=16000000L",
   "-DARDUINO=10607",
   "-DARDUINO_AVR_NANO",
   "-DARDUINO_ARCH_AVR",
   "-IC:\\Users\\5491\\AppData\\Local\\arduino15\\packages\\arduino\\hardware\\avr\\1.8.6\\cores\\arduino",
   "-IC:\\Users\\5491\\AppData\\Local\\arduino15\\packages\\arduino\\hardware\\avr\\1.8.6\\variants\\eightanaloginputs",
   "C:\\Users\\5491\\AppData\\Local\\arduino15\\packages\\arduino\\hardware\\avr\\1.8.6\\cores\\arduino\\wiring.c",
   "-o",
   "D:\\workspace\\ArduinoProjects\\weather station\\summer_17_12_21\\weather_Station_without_rf\\output\\core\\wiring.c.o"
  ],
  "file": "C:\\Users\\5491\\AppData\\Local\\arduino15\\packages\\arduino\\hardware\\avr\\1.8.6\\cores\\arduino\\wiring.c"
 },
 {
  "directory": "d:\\workspace\\ArduinoProjects\\weather station\\summer_17_12_21\\weather_Station_without_rf",
  "arguments": [
   "C:\\Users\\5491\\AppData\\Local\\arduino15\\packages\\arduino\\tools\\avr-gcc\\7.3.0-atmel3.6.1-arduino7/bin/avr-gcc",
   "-c",
   "-g",
   "-Os",
   "-w",
   "-std=gnu11",
   "-ffunction-sections",
   "-fdata-sections",
   "-MMD",
   "-flto",
   "-fno-fat-lto-objects",
   "-mmcu=atmega328p",
   "-DF_CPU=16000000L",
   "-DARDUINO=10607",
   "-DARDUINO_AVR_NANO",
   "-DARDUINO_ARCH_AVR",
   "-IC:\\Users\\5491\\AppData\\Local\\arduino15\\packages\\arduino\\hardware\\avr\\1.8.6\\cores\\arduino",
   "-IC:\\Users\\5491\\AppData\\Local\\arduino15\\packages\\arduino\\hardware\\avr\\1.8.6\\variants\\eightanaloginputs",
   "C:\\Users\\5491\\AppData\\Local\\arduino15\\packages\\arduino\\hardware\\avr\\1.8.6\\cores\\arduino\\wiring_digital.c",
   "-o",
   "D:\\workspace\\ArduinoProjects\\weather station\\summer_17_12_21\\weather_Station_without_rf\\output\\core\\wiring_digital.c.o"
  ],
  "file": "C:\\Users\\5491\\AppData\\Local\\arduino15\\packages\\arduino\\hardware\\avr\\1.8.6\\cores\\arduino\\wiring_digital.c"
 },
 {
  "directory": "d:\\workspace\\ArduinoProjects\\weather station\\summer_17_12_21\\weather_Station_without_rf",
  "arguments": [
   "C:\\Users\\5491\\AppData\\Local\\arduino15\\packages\\arduino\\tools\\avr-gcc\\7.3.0-atmel3.6.1-arduino7/bin/avr-gcc",
   "-c",
   "-g",
   "-Os",
   "-w",
   "-std=gnu11",
   "-ffunction-sections",
   "-fdata-sections",
   "-MMD",
   "-flto",
   "-fno-fat-lto-objects",
   "-mmcu=atmega328p",
   "-DF_CPU=16000000L",
   "-DARDUINO=10607",
   "-DARDUINO_AVR_NANO",
   "-DARDUINO_ARCH_AVR",
   "-IC:\\Users\\5491\\AppData\\Local\\arduino15\\packages\\arduino\\hardware\\avr\\1.8.6\\cores\\arduino",
   "-IC:\\Users\\5491\\AppData\\Local\\arduino15\\packages\\arduino\\hardware\\avr\\1.8.6\\variants\\eightanaloginputs",
   "C:\\Users\\5491\\AppData\\Local\\arduino15\\packages\\arduino\\hardware\\avr\\1.8.6\\cores\\arduino\\wiring_analog.c",
   "-o",
   "D:\\workspace\\ArduinoProjects\\weather station\\summer_17_12_21\\weather_Station_without_rf\\output\\core\\wiring_analog.c.o"
  ],
  "file": "C:\\Users\\5491\\AppData\\Local\\arduino15\\packages\\arduino\\hardware\\avr\\1.8.6\\cores\\arduino\\wiring_analog.c"
 },
 {
  "directory": "d:\\workspace\\ArduinoProjects\\weather station\\summer_17_12_21\\weather_Station_without_rf",
  "arguments": [
   "C:\\Users\\5491\\AppData\\Local\\arduino15\\packages\\arduino\\tools\\avr-gcc\\7.3.0-atmel3.6.1-arduino7/bin/avr-gcc",
   "-c",
   "-g",
   "-Os",
   "-w",
   "-std=gnu11",
   "-ffunction-sections",
   "-fdata-sections",
   "-MMD",
   "-flto",
   "-fno-fat-lto-objects",
   "-mmcu=atmega328p",
   "-DF_CPU=16000000L",
   "-DARDUINO=10607",
   "-DARDUINO_AVR_NANO",
   "-DARDUINO_ARCH_AVR",
   "-IC:\\Users\\5491\\AppData\\Local\\arduino15\\packages\\arduino\\hardware\\avr\\1.8.6\\cores\\arduino",
   "-IC:\\Users\\5491\\AppData\\Local\\arduino15\\packages\\arduino\\hardware\\avr\\1.8.6\\variants\\eightanaloginputs",
   "C:\\Users\\5491\\AppData\\Local\\arduino15\\packages\\arduino\\hardware\\avr\\1.8.6\\cores\\arduino\\wiring_pulse.c",
   "-o",
   "D:\\workspace\\ArduinoProjects\\weather station\\summer_17_12_21\\weather_Station_without_rf\\output\\core\\wiring_pulse.c.o"
  ],
  "file": "C:\\Users\\5491\\AppData\\Local\\arduino15\\packages\\arduino\\hardware\\avr\\1.8.6\\cores\\arduino\\wiring_pulse.c"
 },
 {
  "directory": "d:\\workspace\\ArduinoProjects\\weather station\\summer_17_12_21\\weather_Station_without_rf",
  "arguments": [
   "C:\\Users\\5491\\AppData\\Local\\arduino15\\packages\\arduino\\tools\\avr-gcc\\7.3.0-atmel3.6.1-arduino7/bin/avr-gcc",
   "-c",
   "-g",
   "-Os",
   "-w",
   "-std=gnu11",
   "-ffunction-sections",
   "-fdata-sections",
   "-MMD",
   "-flto",
   "-fno-fat-lto-objects",
   "-mmcu=atmega328p",
   "-DF_CPU=16000000L",
   "-DARDUINO=10607",
   "-DARDUINO_AVR_NANO",
   "-DARDUINO_ARCH_AVR",
   "-IC:\\Users\\5491\\AppData\\Local\\arduino15\\packages\\arduino\\hardware\\avr\\1.8.6\\cores\\arduino",
   "-IC:\\Users\\5491\\AppData\\Local\\arduino15\\packages\\arduino\\hardware\\avr\\1.8.6\\variants\\eightanaloginputs",
   "C:\\Users\\5491\\AppData\\Local\\arduino15\\packages\\arduino\\hardware\\avr\\1.8.6\\cores\\arduino\\wiring_shift.c",
   "-o",
   "D:\\workspace\\ArduinoProjects\\weather station\\summer_17_12_21\\weather_Station_without_rf\\output\\core\\wiring_shift.c.o"
  ],
  "file": "C:\\Users\\5491\\AppData\\Local\\arduino15\\packages\\arduino\\hardware\\avr\\1.8.6\\cores\\arduino\\wiring_shift.c"
 }
]